svg.cp36-win_amd64.pyd
pynanosvg-0.2.0.dist-info/METADATA
pynanosvg-0.2.0.dist-info/RECORD
pynanosvg-0.2.0.dist-info/WHEEL
pynanosvg-0.2.0.dist-info/top_level.txt
svg-stubs/svg.pyi
svg_stubs/py.typed
svg_stubs/svg.pyi
