Metadata-Version: 2.1
Name: pynanosvg
Version: 0.2.0
Summary: Wrapper around nanosvg
Home-page: https://github.com/ethanhs/pynanosvg
Author: Ethan Smith
Author-email: ethan@ethanhs.me
License: MIT
Platform: UNKNOWN
